dummyreaction/__init__.py
dummyreaction/kimmdy-yaml-schema.json
dummyreaction/reaction.py
hat_naive/__init__.py
hat_naive/kimmdy-yaml-schema.json
hat_naive/reaction.py
homolysis/__init__.py
homolysis/kimmdy-yaml-schema.json
homolysis/reaction.py
kimmdy_reactions-1.1.2.dist-info/licenses/LICENSE
kimmdy_reactions-1.1.2.dist-info/METADATA
kimmdy_reactions-1.1.2.dist-info/WHEEL
kimmdy_reactions-1.1.2.dist-info/entry_points.txt
kimmdy_reactions-1.1.2.dist-info/top_level.txt
kimmdy_reactions-1.1.2.dist-info/RECORD
