Metadata-Version: 2.4
Name: kimmdy-reactions
Version: 1.1.2
Summary: Reaction template for KIMMDY
Author-email: Kai Riedmiller <kai.riedmiller@h-its.org>
License-Expression: GPL-3.0-or-later
Classifier: Programming Language :: Python :: 3
Classifier: Operating System :: OS Independent
Requires-Python: >=3.9
License-File: LICENSE
Requires-Dist: MDAnalysis
Provides-Extra: dev
Requires-Dist: kimmdy; extra == "dev"
Requires-Dist: pytest; extra == "dev"
Requires-Dist: tox; extra == "dev"
Requires-Dist: black; extra == "dev"
Requires-Dist: hypothesis; extra == "dev"
Requires-Dist: jupyter; extra == "dev"
Requires-Dist: griffe<1.0.0,>=0.33; extra == "dev"
Requires-Dist: quartodoc; extra == "dev"
Dynamic: license-file
